pyprod/__init__.py
pyprod/__main__.py
pyprod/main.py
pyprod/prod.py
pyprod/utils.py
pyprod/venv.py
pyprod-0.10.2.dist-info/METADATA
pyprod-0.10.2.dist-info/WHEEL
pyprod-0.10.2.dist-info/entry_points.txt
pyprod-0.10.2.dist-info/licenses/LICENSE
pyprod-0.10.2.dist-info/RECORD
