Metadata-Version: 2.4
Name: PyProd
Version: 0.10.2
Summary: PyProd: More Makeable than Make
Project-URL: Homepage, https://github.com/atsuoishimoto/pyprod
Project-URL: Documentation, https://pyprod.readthedocs.io/en/latest/
License-File: LICENSE
Classifier: Development Status :: 3 - Alpha
Classifier: Environment :: Console
Classifier: License :: OSI Approved :: MIT License
Classifier: Operating System :: OS Independent
Classifier: Programming Language :: Python :: 3
Classifier: Topic :: Software Development :: Build Tools
Requires-Python: >=3.10
Requires-Dist: python-dateutil
Requires-Dist: watchdog>=6.0.0
